{
    "model_config": {
        "num_features": 9,
        "hidden_dim": 32,
        "depth": 4,
        "num_heads": 4,
        "mlp_ratio": 4.0,
        "dropout_prob": 0.0,
        "use_flash_attn": false,
        "ema_decay": 0.999,
        "contrastive_loss_weight": 0.1
    },
    "train_config": {
        "data_dir": "Data/",
        "epochs": 200,
        "learning_rate": 0.001,
        "sche_gamma": 0.95,
        "batch_size": 512,
        "random_seed": 42,
        "num_workers": 0,
        "preprocess": "standard",
        "patience": 10,
        "min_delta": 0,
        "use_amp": false,
        "model_type": "TKDAD",
        "dataset_name": "breastw",
        "base_path": "results/TKDAD-d32-lr0.001-contra0.1/breastw/1.0",
        "exp_name": "TKDAD-d32-lr0.001-contra0.1",
        "runs": 10,
        "train_ratio": 1.0
    },
    "mean_metrics": {
        "avg_normal_score": 0.07684719040989876,
        "avg_abnormal_score": 0.4488370954990387,
        "f1": 0.906694560669456,
        "rauc": 0.9585736363979043,
        "ap": 0.9423308887510462
    },
    "std_metrics": {
        "avg_normal_score_std": 0.025894768961291375,
        "avg_abnormal_score_std": 0.14546697597228556,
        "f1_std": 0.020416523679926097,
        "rauc_std": 0.015487102240443765,
        "ap_std": 0.02691187103908048
    },
    "total_time": 97.35181617736816,
    "all_seeds": [
        {
            "run": 0,
            "train_time": 11.494418382644653,
            "test_time": 0.024294614791870117,
            "epochs": 200,
            "rauc": 0.9684496211692865,
            "ap": 0.9515234043935112,
            "f1": 0.9372384937238494,
            "avg_normal_score": 0.1175699308514595,
            "avg_abnormal_score": 0.7316344976425171
        },
        {
            "run": 1,
            "train_time": 7.35293436050415,
            "test_time": 0.02187967300415039,
            "epochs": 137,
            "rauc": 0.9642089788533303,
            "ap": 0.9483583755867818,
            "f1": 0.9121338912133892,
            "avg_normal_score": 0.04246849939227104,
            "avg_abnormal_score": 0.2813189923763275
        },
        {
            "run": 2,
            "train_time": 10.719488620758057,
            "test_time": 0.024446487426757812,
            "epochs": 200,
            "rauc": 0.968129217083192,
            "ap": 0.9663486670451366,
            "f1": 0.895397489539749,
            "avg_normal_score": 0.06063655763864517,
            "avg_abnormal_score": 0.43378061056137085
        },
        {
            "run": 3,
            "train_time": 6.149761199951172,
            "test_time": 0.020844697952270508,
            "epochs": 112,
            "rauc": 0.9724640958950582,
            "ap": 0.9707708705995447,
            "f1": 0.9246861924686193,
            "avg_normal_score": 0.03878066688776016,
            "avg_abnormal_score": 0.2976556122303009
        },
        {
            "run": 4,
            "train_time": 10.79904842376709,
            "test_time": 0.02564859390258789,
            "epochs": 200,
            "rauc": 0.9702401145915791,
            "ap": 0.9525025362805658,
            "f1": 0.9205020920502092,
            "avg_normal_score": 0.08074736595153809,
            "avg_abnormal_score": 0.5695338845252991
        },
        {
            "run": 5,
            "train_time": 10.86968207359314,
            "test_time": 0.024517297744750977,
            "epochs": 200,
            "rauc": 0.9211805948207622,
            "ap": 0.8763336182420555,
            "f1": 0.8702928870292888,
            "avg_normal_score": 0.09738088399171829,
            "avg_abnormal_score": 0.3675319254398346
        },
        {
            "run": 6,
            "train_time": 10.81970500946045,
            "test_time": 0.024416208267211914,
            "epochs": 200,
            "rauc": 0.9474725771796901,
            "ap": 0.9135755794585783,
            "f1": 0.895397489539749,
            "avg_normal_score": 0.11372549086809158,
            "avg_abnormal_score": 0.6537476778030396
        },
        {
            "run": 7,
            "train_time": 10.968930721282959,
            "test_time": 0.023145675659179688,
            "epochs": 200,
            "rauc": 0.9711259376531344,
            "ap": 0.963214006529961,
            "f1": 0.9288702928870293,
            "avg_normal_score": 0.08191404491662979,
            "avg_abnormal_score": 0.3778015971183777
        },
        {
            "run": 8,
            "train_time": 8.839617252349854,
            "test_time": 0.021075963973999023,
            "epochs": 163,
            "rauc": 0.9568019902747936,
            "ap": 0.942069252443074,
            "f1": 0.899581589958159,
            "avg_normal_score": 0.05866159126162529,
            "avg_abnormal_score": 0.3387191891670227
        },
        {
            "run": 9,
            "train_time": 7.35554838180542,
            "test_time": 0.020859956741333008,
            "epochs": 136,
            "rauc": 0.9456632364582155,
            "ap": 0.9386125769312544,
            "f1": 0.8828451882845189,
            "avg_normal_score": 0.07658687233924866,
            "avg_abnormal_score": 0.436646968126297
        }
    ]
}