{
    "model_config": {
        "num_features": 62,
        "hidden_dim": 128,
        "depth": 4,
        "depth_enc": null,
        "depth_dec": null,
        "num_heads": 4,
        "mlp_ratio": 4.0,
        "dropout_prob": 0.0,
        "temperature": 0.2,
        "contrastive_loss_weight": 0.01,
        "use_flash_attn": false
    },
    "train_config": {
        "data_dir": "Data/",
        "epochs": 200,
        "learning_rate": 0.001,
        "sche_gamma": 0.95,
        "batch_size": 128,
        "random_seed": 42,
        "num_workers": 0,
        "preprocess": "standard",
        "patience": 10,
        "min_delta": 0,
        "use_amp": false,
        "model_type": "TAECL",
        "dataset_name": "campaign",
        "base_path": "results/TAECL-250124-ph-knn_attn1/campaign/1.0",
        "exp_name": "TAECL-250124-ph-knn_attn1",
        "runs": 10,
        "train_ratio": 1.0,
        "base_pth_path": "results/TAECL-250124/campaign/1.0"
    },
    "mean_metrics": {
        "rauc": 0.7460207166154664,
        "ap": 0.4556600713617689,
        "f1": 0.4644396551724138
    },
    "std_metrics": {
        "rauc_std": 0.026630134253658233,
        "ap_std": 0.042131631280233846,
        "f1_std": 0.031106238883911574
    },
    "total_time": 559.6928112506866,
    "all_seeds": [
        {
            "rauc": 0.7381570244892875,
            "ap": 0.4390761084071396,
            "f1": 0.4415948275862069,
            "run": 0,
            "test_time": 65.29907083511353
        },
        {
            "rauc": 0.7268131800221154,
            "ap": 0.4193218271998478,
            "f1": 0.44418103448275864,
            "run": 1,
            "test_time": 52.661367893218994
        },
        {
            "rauc": 0.7729498205949286,
            "ap": 0.4656733470108498,
            "f1": 0.4857758620689655,
            "run": 2,
            "test_time": 44.21750450134277
        },
        {
            "rauc": 0.7829948063104542,
            "ap": 0.5100928432741061,
            "f1": 0.5012931034482758,
            "run": 3,
            "test_time": 52.00078535079956
        },
        {
            "rauc": 0.7560613958780706,
            "ap": 0.4772572851569347,
            "f1": 0.4870689655172414,
            "run": 4,
            "test_time": 52.304311752319336
        },
        {
            "rauc": 0.7332982570393963,
            "ap": 0.4256089480245624,
            "f1": 0.4366379310344828,
            "run": 5,
            "test_time": 52.05384874343872
        },
        {
            "rauc": 0.7599141999845266,
            "ap": 0.49571327763729495,
            "f1": 0.48017241379310344,
            "run": 6,
            "test_time": 52.35494351387024
        },
        {
            "rauc": 0.7565392865499504,
            "ap": 0.48643300455109867,
            "f1": 0.48017241379310344,
            "run": 7,
            "test_time": 50.82283639907837
        },
        {
            "rauc": 0.7505589720462085,
            "ap": 0.4754614783097193,
            "f1": 0.49008620689655175,
            "run": 8,
            "test_time": 65.92832565307617
        },
        {
            "rauc": 0.6829202232397263,
            "ap": 0.3619625940461354,
            "f1": 0.39741379310344827,
            "run": 9,
            "test_time": 67.78767514228821
        }
    ]
}