{
    "model_config": {
        "num_features": 16,
        "hidden_dim": 128,
        "depth": 4,
        "depth_enc": null,
        "depth_dec": null,
        "num_heads": 4,
        "mlp_ratio": 4.0,
        "dropout_prob": 0.0,
        "temperature": 0.2,
        "contra_loss_weight": 0.01,
        "dacl_alpha": 0.9,
        "use_flash_attn": false,
        "use_swap": false
    },
    "train_config": {
        "data_dir": "Data/",
        "epochs": 200,
        "learning_rate": 0.001,
        "sche_gamma": 0.95,
        "batch_size": 128,
        "random_seed": 42,
        "num_workers": 0,
        "preprocess": "standard",
        "patience": 10,
        "min_delta": 0,
        "use_amp": false,
        "model_type": "TAEDACLv3",
        "dataset_name": "pendigits",
        "base_path": "results/TAEDACLv3-260126-cw0.1-ap0.95-ph-comb_knn_attn1_w0.1/pendigits/1.0",
        "exp_name": "TAEDACLv3-260126-cw0.1-ap0.95-ph-comb_knn_attn1_w0.1",
        "runs": 10,
        "train_ratio": 1.0,
        "base_pth_path": "results/TAEDACLv3-260126-cw0.1-ap0.95/pendigits/1.0"
    },
    "mean_metrics": {
        "rauc": 0.936174698104993,
        "ap": 0.33442667577793717,
        "f1": 0.3506410256410256
    },
    "std_metrics": {
        "rauc_std": 0.02186707545389045,
        "ap_std": 0.10847173784084306,
        "f1_std": 0.10821948197419894
    },
    "total_time": 102.62454795837402,
    "all_seeds": [
        {
            "rauc": 0.9501863690871734,
            "ap": 0.36601930016805845,
            "f1": 0.3525641025641026,
            "run": 0,
            "test_time": 11.149441480636597
        },
        {
            "rauc": 0.9308448477349283,
            "ap": 0.28986150746147005,
            "f1": 0.32051282051282054,
            "run": 1,
            "test_time": 9.173758745193481
        },
        {
            "rauc": 0.945683722493374,
            "ap": 0.3663024572427108,
            "f1": 0.42948717948717946,
            "run": 2,
            "test_time": 9.774868249893188
        },
        {
            "rauc": 0.9194793886482895,
            "ap": 0.24514336403490117,
            "f1": 0.2948717948717949,
            "run": 3,
            "test_time": 9.5211820602417
        },
        {
            "rauc": 0.948070621663115,
            "ap": 0.40724726523584237,
            "f1": 0.46153846153846156,
            "run": 4,
            "test_time": 10.323638677597046
        },
        {
            "rauc": 0.9238636450432697,
            "ap": 0.2967267585539391,
            "f1": 0.3333333333333333,
            "run": 5,
            "test_time": 9.46233582496643
        },
        {
            "rauc": 0.8919307531908068,
            "ap": 0.19247421486581348,
            "f1": 0.19230769230769232,
            "run": 6,
            "test_time": 9.757037878036499
        },
        {
            "rauc": 0.9212094131665177,
            "ap": 0.21678796323112115,
            "f1": 0.1794871794871795,
            "run": 7,
            "test_time": 10.253581047058105
        },
        {
            "rauc": 0.961792427610122,
            "ap": 0.3781515898496688,
            "f1": 0.3974358974358974,
            "run": 8,
            "test_time": 9.659583568572998
        },
        {
            "rauc": 0.9686857924123339,
            "ap": 0.5855523371358469,
            "f1": 0.5448717948717948,
            "run": 9,
            "test_time": 9.762993812561035
        }
    ]
}