{
    "model_config": {
        "num_features": 122,
        "hidden_dim": 128,
        "depth": 4,
        "depth_enc": null,
        "depth_dec": null,
        "num_heads": 4,
        "mlp_ratio": 4.0,
        "dropout_prob": 0.0,
        "temperature": 0.2,
        "imix_loss_weight": 0.01,
        "mixup_alpha": 0.9,
        "projector_dim": null,
        "use_flash_attn": true
    },
    "train_config": {
        "data_dir": "Data/",
        "epochs": 50,
        "learning_rate": 0.001,
        "sche_gamma": 0.95,
        "batch_size": 1024,
        "random_seed": 42,
        "num_workers": 0,
        "preprocess": "standard",
        "patience": 20,
        "min_delta": 0,
        "use_amp": true,
        "model_type": "TAEIMIX",
        "dataset_name": "nslkdd",
        "base_path": "results/TAEIMIX-260125-iw0.01-ap0.9-ph-comb_knn1_w2.0/nslkdd/1.0",
        "exp_name": "TAEIMIX-260125-iw0.01-ap0.9-ph-comb_knn1_w2.0",
        "runs": 10,
        "train_ratio": 1.0,
        "base_pth_path": "results/TAEIMIX-260125-iw0.01-ap0.9/nslkdd/1.0"
    },
    "mean_metrics": {
        "rauc": 0.6547146318647068,
        "ap": 0.7628353638552763,
        "f1": 0.7655252297083562
    },
    "std_metrics": {
        "rauc_std": 0.1550606064487753,
        "ap_std": 0.07855308868180007,
        "f1_std": 0.08571844512006364
    },
    "total_time": 5865.31344294548,
    "all_seeds": [
        {
            "rauc": 0.6855745338460695,
            "ap": 0.7802469301777154,
            "f1": 0.7775766188427521,
            "run": 0,
            "test_time": 616.5732705593109
        },
        {
            "rauc": 0.6267929771925138,
            "ap": 0.7676101891557455,
            "f1": 0.6986009811301166,
            "run": 1,
            "test_time": 604.8429863452911
        },
        {
            "rauc": 0.5196311953122057,
            "ap": 0.6922710485867574,
            "f1": 0.746048225919485,
            "run": 2,
            "test_time": 579.1958453655243
        },
        {
            "rauc": 0.33575403406824844,
            "ap": 0.6148026186784274,
            "f1": 0.5890079906450985,
            "run": 3,
            "test_time": 589.0091607570648
        },
        {
            "rauc": 0.8628520436851874,
            "ap": 0.891684018042003,
            "f1": 0.883224751472993,
            "run": 4,
            "test_time": 590.3567340373993
        },
        {
            "rauc": 0.4910486830592659,
            "ap": 0.685071013326723,
            "f1": 0.6722428426817556,
            "run": 5,
            "test_time": 579.4543352127075
        },
        {
            "rauc": 0.7552432457176065,
            "ap": 0.776305625406513,
            "f1": 0.8542580527941444,
            "run": 6,
            "test_time": 570.2368123531342
        },
        {
            "rauc": 0.8260843690909224,
            "ap": 0.8632878253556151,
            "f1": 0.8308199444545383,
            "run": 7,
            "test_time": 578.0658445358276
        },
        {
            "rauc": 0.7164098168032305,
            "ap": 0.7553812963885997,
            "f1": 0.801217328107561,
            "run": 8,
            "test_time": 574.3887269496918
        },
        {
            "rauc": 0.7277554198718184,
            "ap": 0.8016930734346638,
            "f1": 0.8022555610351182,
            "run": 9,
            "test_time": 574.2816205024719
        }
    ]
}