{
    "model_config": {
        "hidden_dim": 64,
        "depth": 4,
        "num_heads": 4,
        "mlp_ratio": 4.0,
        "dropout_prob": 0.0,
        "num_prototypes": 10,
        "temperature": 0.1,
        "sinkhorn_iters": 3,
        "sinkhorn_eps": 0.1,
        "contrastive_loss_weight": 1.0,
        "use_flash_attn": false,
        "num_features": 33
    },
    "train_config": {
        "data_dir": "Data/",
        "epochs": 250,
        "learning_rate": 0.01,
        "sche_gamma": 0.95,
        "batch_size": 32,
        "random_seed": 42,
        "num_workers": 0,
        "preprocess": "standard",
        "patience": 5,
        "use_amp": false,
        "model_type": "ProtoAD",
        "dataset_name": "ionosphere",
        "base_path": "results/ProtoAD-d64-proto10-eps0.1-contra1.0-temp0.1/ionosphere/1.0",
        "exp_name": "ProtoAD-d64-proto10-eps0.1-contra1.0-temp0.1",
        "runs": 10,
        "train_ratio": 1.0,
        "run": 9
    },
    "mean_metrics": {
        "rauc": 0.9371049304677623,
        "ap": 0.9489968680183045,
        "f1": 0.8539682539682539,
        "entropy_rauc": 0.34633024301165893,
        "entropy_ap": 0.44853078643825767,
        "entropy_f1": 0.39444444444444443,
        "avg_normal_entropy": 1.7987548232078552,
        "avg_abnormal_entropy": 1.6308718919754028,
        "avg_normal_recon": 0.6885037064552307,
        "avg_abnormal_recon": 3.55153169631958
    },
    "std_metrics": {
        "rauc_std": 0.0164221388150467,
        "ap_std": 0.014760263223615618,
        "f1_std": 0.029949146450973355,
        "entropy_rauc_std": 0.07224406972449074,
        "entropy_ap_std": 0.04698655499436304,
        "entropy_f1_std": 0.061275803641135294,
        "avg_normal_entropy_std": 0.16421457582422333,
        "avg_abnormal_entropy_std": 0.19446032861498558,
        "avg_normal_recon_std": 0.09230474587292911,
        "avg_abnormal_recon_std": 0.3329349775072658
    },
    "total_time": 21.931171894073486,
    "all_seeds": [
        {
            "run": 0,
            "train_time": 2.7348787784576416,
            "test_time": 0.06458616256713867,
            "epochs": 10,
            "rauc": 0.9312403427447676,
            "ap": 0.9423648138231977,
            "f1": 0.8571428571428571,
            "entropy_rauc": 0.2494732406236831,
            "entropy_ap": 0.43935132196877724,
            "entropy_f1": 0.30158730158730157,
            "avg_normal_entropy": 1.992756724357605,
            "avg_abnormal_entropy": 1.748172402381897,
            "avg_normal_recon": 0.6567840576171875,
            "avg_abnormal_recon": 3.509542942047119
        },
        {
            "run": 1,
            "train_time": 2.5863630771636963,
            "test_time": 0.06314706802368164,
            "epochs": 15,
            "rauc": 0.9377721590110971,
            "ap": 0.9510724125354774,
            "f1": 0.8571428571428571,
            "entropy_rauc": 0.2901390644753476,
            "entropy_ap": 0.4032887911398886,
            "entropy_f1": 0.3968253968253968,
            "avg_normal_entropy": 1.6736222505569458,
            "avg_abnormal_entropy": 1.5482503175735474,
            "avg_normal_recon": 0.6286045908927917,
            "avg_abnormal_recon": 3.321345806121826
        },
        {
            "run": 2,
            "train_time": 1.22322416305542,
            "test_time": 0.061257123947143555,
            "epochs": 7,
            "rauc": 0.9592639415648264,
            "ap": 0.9690600129472902,
            "f1": 0.9047619047619048,
            "entropy_rauc": 0.3329119258322798,
            "entropy_ap": 0.41673948061658656,
            "entropy_f1": 0.3333333333333333,
            "avg_normal_entropy": 1.7162564992904663,
            "avg_abnormal_entropy": 1.3233439922332764,
            "avg_normal_recon": 0.7377645373344421,
            "avg_abnormal_recon": 4.219723224639893
        },
        {
            "run": 3,
            "train_time": 1.9278857707977295,
            "test_time": 0.04276442527770996,
            "epochs": 11,
            "rauc": 0.907220115184717,
            "ap": 0.9232220634452106,
            "f1": 0.7936507936507936,
            "entropy_rauc": 0.34822306503722433,
            "entropy_ap": 0.43149491528542966,
            "entropy_f1": 0.373015873015873,
            "avg_normal_entropy": 1.729756236076355,
            "avg_abnormal_entropy": 1.5389522314071655,
            "avg_normal_recon": 0.6236174702644348,
            "avg_abnormal_recon": 2.9530115127563477
        },
        {
            "run": 4,
            "train_time": 1.9264051914215088,
            "test_time": 0.07108616828918457,
            "epochs": 11,
            "rauc": 0.935173479421267,
            "ap": 0.9474310586074791,
            "f1": 0.8333333333333334,
            "entropy_rauc": 0.4507655569602472,
            "entropy_ap": 0.49902977687233907,
            "entropy_f1": 0.5,
            "avg_normal_entropy": 1.5785698890686035,
            "avg_abnormal_entropy": 1.5313998460769653,
            "avg_normal_recon": 0.6552650928497314,
            "avg_abnormal_recon": 3.226715564727783
        },
        {
            "run": 5,
            "train_time": 1.355405330657959,
            "test_time": 0.0731201171875,
            "epochs": 8,
            "rauc": 0.9563843236409608,
            "ap": 0.966835091068372,
            "f1": 0.8888888888888888,
            "entropy_rauc": 0.35991712319145946,
            "entropy_ap": 0.4995786230538739,
            "entropy_f1": 0.373015873015873,
            "avg_normal_entropy": 1.8825924396514893,
            "avg_abnormal_entropy": 1.7482963800430298,
            "avg_normal_recon": 0.632408857345581,
            "avg_abnormal_recon": 3.6837007999420166
        },
        {
            "run": 6,
            "train_time": 1.9369170665740967,
            "test_time": 0.06697583198547363,
            "epochs": 11,
            "rauc": 0.9120663014468323,
            "ap": 0.9256960432018815,
            "f1": 0.8253968253968254,
            "entropy_rauc": 0.4966287399915719,
            "entropy_ap": 0.5432765271921789,
            "entropy_f1": 0.5079365079365079,
            "avg_normal_entropy": 2.063701868057251,
            "avg_abnormal_entropy": 2.02778697013855,
            "avg_normal_recon": 0.8625869154930115,
            "avg_abnormal_recon": 3.821056842803955
        },
        {
            "run": 7,
            "train_time": 1.6181581020355225,
            "test_time": 0.06011819839477539,
            "epochs": 9,
            "rauc": 0.9521702486304257,
            "ap": 0.9613973082320064,
            "f1": 0.8650793650793651,
            "entropy_rauc": 0.3350891979210564,
            "entropy_ap": 0.4497391457352488,
            "entropy_f1": 0.3888888888888889,
            "avg_normal_entropy": 1.793853759765625,
            "avg_abnormal_entropy": 1.5914440155029297,
            "avg_normal_recon": 0.632204532623291,
            "avg_abnormal_recon": 3.6640095710754395
        },
        {
            "run": 8,
            "train_time": 1.7758986949920654,
            "test_time": 0.06326436996459961,
            "epochs": 10,
            "rauc": 0.9358055906728473,
            "ap": 0.9473126306319742,
            "f1": 0.8492063492063492,
            "entropy_rauc": 0.2737744065177694,
            "entropy_ap": 0.3955155639124131,
            "entropy_f1": 0.38095238095238093,
            "avg_normal_entropy": 1.5804466009140015,
            "avg_abnormal_entropy": 1.4361907243728638,
            "avg_normal_recon": 0.8566260933876038,
            "avg_abnormal_recon": 3.700664758682251
        },
        {
            "run": 9,
            "train_time": 2.086117744445801,
            "test_time": 0.06386566162109375,
            "epochs": 12,
            "rauc": 0.943952802359882,
            "ap": 0.9555772456901561,
            "f1": 0.8650793650793651,
            "entropy_rauc": 0.32638010956595026,
            "entropy_ap": 0.4072937186058406,
            "entropy_f1": 0.3888888888888889,
            "avg_normal_entropy": 1.97599196434021,
            "avg_abnormal_entropy": 1.8148820400238037,
            "avg_normal_recon": 0.5991749167442322,
            "avg_abnormal_recon": 3.41554594039917
        }
    ]
}