{
    "model_config": {
        "num_features": 274,
        "hidden_dim": 64,
        "depth": 4,
        "depth_enc": null,
        "depth_dec": null,
        "num_heads": 4,
        "mlp_ratio": 4.0,
        "dropout_prob": 0.0,
        "use_flash_attn": false
    },
    "train_config": {
        "data_dir": "Data/",
        "epochs": 200,
        "learning_rate": 0.01,
        "sche_gamma": 0.95,
        "batch_size": 512,
        "random_seed": 42,
        "num_workers": 0,
        "preprocess": "standard",
        "patience": 10,
        "min_delta": 0,
        "use_amp": false,
        "model_type": "TADAM",
        "dataset_name": "arrhythmia",
        "base_path": "results/TADAM-d64-lr0.01-knn64/arrhythmia/1.0",
        "exp_name": "TADAM-d64-lr0.01-knn64",
        "runs": 10,
        "train_ratio": 1.0
    },
    "mean_metrics": {
        "rauc": 0.8126157952582822,
        "ap": 0.615699072699672,
        "f1": 0.5924242424242425
    },
    "std_metrics": {
        "rauc_std": 0.02493350905939429,
        "ap_std": 0.056396959260878045,
        "f1_std": 0.04362478802693324
    },
    "total_time": 460.4188482761383,
    "all_seeds": [
        {
            "rauc": 0.8199874391584236,
            "ap": 0.6288882576917048,
            "f1": 0.5757575757575758,
            "run": 0,
            "epochs": 112,
            "train_time": 43.65159368515015,
            "test_time": 3.3472158908843994
        },
        {
            "rauc": 0.8197519233788665,
            "ap": 0.6709629539676665,
            "f1": 0.6212121212121212,
            "run": 1,
            "epochs": 119,
            "train_time": 48.95526337623596,
            "test_time": 3.140636682510376
        },
        {
            "rauc": 0.7848170827445439,
            "ap": 0.5427254746333809,
            "f1": 0.6060606060606061,
            "run": 2,
            "epochs": 40,
            "train_time": 16.87822151184082,
            "test_time": 3.825960397720337
        },
        {
            "rauc": 0.8506044905008635,
            "ap": 0.6992446249492209,
            "f1": 0.6212121212121212,
            "run": 3,
            "epochs": 121,
            "train_time": 49.5776104927063,
            "test_time": 3.2402238845825195
        },
        {
            "rauc": 0.7960433349034386,
            "ap": 0.5495710479165588,
            "f1": 0.5454545454545454,
            "run": 4,
            "epochs": 119,
            "train_time": 47.62554359436035,
            "test_time": 3.1848583221435547
        },
        {
            "rauc": 0.7644057151829172,
            "ap": 0.5168698161585292,
            "f1": 0.48484848484848486,
            "run": 5,
            "epochs": 119,
            "train_time": 48.05110216140747,
            "test_time": 3.192613363265991
        },
        {
            "rauc": 0.8235201758517819,
            "ap": 0.6503985792576323,
            "f1": 0.6060606060606061,
            "run": 6,
            "epochs": 106,
            "train_time": 39.898603200912476,
            "test_time": 3.23994779586792
        },
        {
            "rauc": 0.7983199874391584,
            "ap": 0.6331322604847786,
            "f1": 0.6212121212121212,
            "run": 7,
            "epochs": 123,
            "train_time": 48.58741331100464,
            "test_time": 3.2058632373809814
        },
        {
            "rauc": 0.8381221541843304,
            "ap": 0.6274123880583413,
            "f1": 0.6363636363636364,
            "run": 8,
            "epochs": 105,
            "train_time": 39.10752248764038,
            "test_time": 3.3871052265167236
        },
        {
            "rauc": 0.830585649238499,
            "ap": 0.637785323878906,
            "f1": 0.6060606060606061,
            "run": 9,
            "epochs": 117,
            "train_time": 43.211944818496704,
            "test_time": 3.2242329120635986
        }
    ]
}