{
    "model_config": {
        "data_dir": "Data/",
        "random_seed": 42,
        "num_workers": 0,
        "batch_size": 512,
        "preprocess": "standard",
        "model_type": "GOAD",
        "data_dim": 6,
        "dataset_name": "dependency_anomalies_38_thyroid_42",
        "train_ratio": 1.0,
        "base_path": "results/GOAD/dependency_anomalies_38_thyroid_42/1.0",
        "run": 9
    },
    "mean_metrics": {
        "AUC-ROC": 0.7761401355773726,
        "AUC-PR": 0.15407026151877556,
        "f1": 0.2387096774193548
    },
    "total_time": 164.41020512580872,
    "all_seeds": [
        {
            "run": 0,
            "AUC-ROC": 0.7870441795231417,
            "AUC-PR": 0.1670030519225526,
            "f1": 0.25806451612903225
        },
        {
            "run": 1,
            "AUC-ROC": 0.778015427769986,
            "AUC-PR": 0.15734031717260696,
            "f1": 0.23655913978494625
        },
        {
            "run": 2,
            "AUC-ROC": 0.7783835904628331,
            "AUC-PR": 0.16053817968576473,
            "f1": 0.26881720430107525
        },
        {
            "run": 3,
            "AUC-ROC": 0.7785121552127163,
            "AUC-PR": 0.1496289524640657,
            "f1": 0.21505376344086022
        },
        {
            "run": 4,
            "AUC-ROC": 0.7858052828424498,
            "AUC-PR": 0.1648338285383528,
            "f1": 0.26881720430107525
        },
        {
            "run": 5,
            "AUC-ROC": 0.7734747545582048,
            "AUC-PR": 0.14832262332560703,
            "f1": 0.22580645161290322
        },
        {
            "run": 6,
            "AUC-ROC": 0.7669179523141656,
            "AUC-PR": 0.1430470842901354,
            "f1": 0.22580645161290322
        },
        {
            "run": 7,
            "AUC-ROC": 0.7684957924263675,
            "AUC-PR": 0.1445201865135268,
            "f1": 0.20430107526881722
        },
        {
            "run": 8,
            "AUC-ROC": 0.7736968209443664,
            "AUC-PR": 0.15649932720560752,
            "f1": 0.24731182795698925
        },
        {
            "run": 9,
            "AUC-ROC": 0.7710553997194951,
            "AUC-PR": 0.14896906406953608,
            "f1": 0.23655913978494625
        }
    ]
}