{
    "model_config": {
        "num_features": 33,
        "hidden_dim": 64,
        "depth": 4,
        "depth_enc": null,
        "depth_dec": null,
        "num_heads": 4,
        "mlp_ratio": 4.0,
        "dropout_prob": 0.0,
        "temperature": 0.2,
        "imix_loss_weight": 0.01,
        "mixup_alpha": 0.9,
        "projector_dim": null,
        "use_flash_attn": false
    },
    "train_config": {
        "data_dir": "Data/",
        "epochs": 200,
        "learning_rate": 0.01,
        "sche_gamma": 0.95,
        "batch_size": 512,
        "random_seed": 42,
        "num_workers": 0,
        "preprocess": "standard",
        "patience": 10,
        "min_delta": 0,
        "use_amp": false,
        "model_type": "TAEIMIX",
        "dataset_name": "ionosphere",
        "base_path": "results/TAEIMIX-260125-iw0.01-ap0.9-ep200-ep60_combined/ionosphere/1.0",
        "exp_name": "TAEIMIX-260125-iw0.01-ap0.9-ep200-ep60_combined",
        "runs": 10,
        "train_ratio": 1.0
    },
    "start_time_kst": "2026-01-25T15:58:59+09:00",
    "mean_metrics": {
        "rauc": 0.9751861216462986,
        "ap": 0.980776645588611,
        "f1": 0.9238095238095239,
        "avg_normal": 0.16560209952294827,
        "avg_abnormal": 2.9133691072463987
    },
    "std_metrics": {
        "rauc_std": 0.008850340658820106,
        "ap_std": 0.007151285559805635,
        "f1_std": 0.021936944382674996,
        "avg_normal_std": 0.08724763751953006,
        "avg_abnormal_std": 0.28540566398276596
    },
    "total_time": 140.5380983352661,
    "all_seeds": [
        {
            "rauc": 0.9860935524652339,
            "ap": 0.9900931454803411,
            "f1": 0.9523809523809523,
            "avg_normal": 0.11520946025848389,
            "avg_abnormal": 2.981574773788452,
            "run": 0,
            "epochs": 155,
            "train_time": 13.877136945724487,
            "test_time": 0.04965376853942871
        },
        {
            "rauc": 0.9583508919792106,
            "ap": 0.9666015523975447,
            "f1": 0.8809523809523809,
            "avg_normal": 0.12529775500297546,
            "avg_abnormal": 2.5394680500030518,
            "run": 1,
            "epochs": 161,
            "train_time": 14.489596128463745,
            "test_time": 0.05122017860412598
        },
        {
            "rauc": 0.9627054361567636,
            "ap": 0.9721376072722483,
            "f1": 0.9047619047619048,
            "avg_normal": 0.3950757384300232,
            "avg_abnormal": 3.5846924781799316,
            "run": 2,
            "epochs": 181,
            "train_time": 15.933762788772583,
            "test_time": 0.04813861846923828
        },
        {
            "rauc": 0.976401179941003,
            "ap": 0.9820008387979416,
            "f1": 0.9206349206349206,
            "avg_normal": 0.05442457273602486,
            "avg_abnormal": 2.5318150520324707,
            "run": 3,
            "epochs": 119,
            "train_time": 10.788847208023071,
            "test_time": 0.04941225051879883
        },
        {
            "rauc": 0.9853912066301447,
            "ap": 0.9889430597575999,
            "f1": 0.9444444444444444,
            "avg_normal": 0.11278264969587326,
            "avg_abnormal": 2.773939371109009,
            "run": 4,
            "epochs": 149,
            "train_time": 13.35722279548645,
            "test_time": 0.04911088943481445
        },
        {
            "rauc": 0.9830734653743504,
            "ap": 0.9872178095348937,
            "f1": 0.9365079365079365,
            "avg_normal": 0.15184810757637024,
            "avg_abnormal": 3.017164468765259,
            "run": 5,
            "epochs": 155,
            "train_time": 12.437253713607788,
            "test_time": 0.04577231407165527
        },
        {
            "rauc": 0.9686753757550218,
            "ap": 0.9751810879314378,
            "f1": 0.8968253968253969,
            "avg_normal": 0.16063880920410156,
            "avg_abnormal": 2.878932476043701,
            "run": 6,
            "epochs": 155,
            "train_time": 13.903393268585205,
            "test_time": 0.04595232009887695
        },
        {
            "rauc": 0.97724399494311,
            "ap": 0.9822729237716015,
            "f1": 0.9285714285714286,
            "avg_normal": 0.21691887080669403,
            "avg_abnormal": 3.1037352085113525,
            "run": 7,
            "epochs": 184,
            "train_time": 15.647464275360107,
            "test_time": 0.048336029052734375
        },
        {
            "rauc": 0.9754881303553871,
            "ap": 0.9801996100670427,
            "f1": 0.9285714285714286,
            "avg_normal": 0.18715843558311462,
            "avg_abnormal": 2.8807504177093506,
            "run": 8,
            "epochs": 148,
            "train_time": 13.021077871322632,
            "test_time": 0.046456336975097656
        },
        {
            "rauc": 0.9784379828627616,
            "ap": 0.9831188208754592,
            "f1": 0.9444444444444444,
            "avg_normal": 0.13666659593582153,
            "avg_abnormal": 2.841618776321411,
            "run": 9,
            "epochs": 162,
            "train_time": 14.656334638595581,
            "test_time": 0.04939842224121094
        }
    ]
}