{
    "model_config": {
        "hidden_dim": 64,
        "depth": 4,
        "num_heads": 4,
        "mlp_ratio": 4.0,
        "dropout_prob": 0.0,
        "num_prototypes": 128,
        "temperature": 0.1,
        "sinkhorn_iters": 3,
        "sinkhorn_eps": 0.05,
        "contrastive_loss_weight": 0.1,
        "use_flash_attn": false,
        "num_features": 9
    },
    "train_config": {
        "data_dir": "Data/",
        "epochs": 250,
        "learning_rate": 0.01,
        "sche_gamma": 0.95,
        "batch_size": 64,
        "random_seed": 42,
        "num_workers": 0,
        "preprocess": "standard",
        "patience": 20,
        "use_amp": false,
        "model_type": "ProtoAD",
        "dataset_name": "breastw",
        "base_path": "results/ProtoAD-d64-proto128-eps0.05-contra0.1-temp0.1/breastw/1.0",
        "exp_name": "ProtoAD-d64-proto128-eps0.05-contra0.1-temp0.1",
        "runs": 10,
        "train_ratio": 1.0,
        "run": 9
    },
    "mean_metrics": {
        "rauc": 0.9834275698292435,
        "ap": 0.9809002725808952,
        "f1": 0.9430962343096236,
        "entropy_rauc": 0.2772296354932338,
        "entropy_ap": 0.385826217477947,
        "entropy_f1": 0.3594142259414225,
        "avg_normal_entropy": 2.4230966567993164,
        "avg_abnormal_entropy": 2.237867522239685,
        "avg_normal_recon": 0.44500243067741396,
        "avg_abnormal_recon": 13.194512033462525
    },
    "std_metrics": {
        "rauc_std": 0.0036055139492059446,
        "ap_std": 0.005840490844576362,
        "f1_std": 0.00920502092050209,
        "entropy_rauc_std": 0.09780480115474566,
        "entropy_ap_std": 0.029859382418953022,
        "entropy_f1_std": 0.0758338622998445,
        "avg_normal_entropy_std": 0.02886020642288781,
        "avg_abnormal_entropy_std": 0.09423292910114175,
        "avg_normal_recon_std": 0.13623392448719107,
        "avg_abnormal_recon_std": 2.8940943294516486
    },
    "total_time": 149.5775022506714,
    "all_seeds": [
        {
            "run": 0,
            "train_time": 6.058250665664673,
            "test_time": 0.030884981155395508,
            "epochs": 76,
            "rauc": 0.9828678050435373,
            "ap": 0.9814866945992338,
            "f1": 0.9456066945606695,
            "entropy_rauc": 0.10594066870217497,
            "entropy_ap": 0.33795134873088717,
            "entropy_f1": 0.21338912133891214,
            "avg_normal_entropy": 2.4282429218292236,
            "avg_abnormal_entropy": 2.0858237743377686,
            "avg_normal_recon": 0.5793514847755432,
            "avg_abnormal_recon": 16.370607376098633
        },
        {
            "run": 1,
            "train_time": 23.194414138793945,
            "test_time": 0.06496334075927734,
            "epochs": 150,
            "rauc": 0.9862603188963022,
            "ap": 0.9858738128659014,
            "f1": 0.9497907949790795,
            "entropy_rauc": 0.18668249839797954,
            "entropy_ap": 0.3580721133141186,
            "entropy_f1": 0.3054393305439331,
            "avg_normal_entropy": 2.4386043548583984,
            "avg_abnormal_entropy": 2.1857187747955322,
            "avg_normal_recon": 0.3471045196056366,
            "avg_abnormal_recon": 13.1144380569458
        },
        {
            "run": 2,
            "train_time": 15.042435884475708,
            "test_time": 0.06557703018188477,
            "epochs": 91,
            "rauc": 0.9909344490934449,
            "ap": 0.9910707469886053,
            "f1": 0.9581589958158996,
            "entropy_rauc": 0.40316257680274414,
            "entropy_ap": 0.4263881353618829,
            "entropy_f1": 0.4769874476987448,
            "avg_normal_entropy": 2.415132999420166,
            "avg_abnormal_entropy": 2.3238461017608643,
            "avg_normal_recon": 0.30293384194374084,
            "avg_abnormal_recon": 12.29002857208252
        },
        {
            "run": 3,
            "train_time": 12.615937948226929,
            "test_time": 0.06643033027648926,
            "epochs": 76,
            "rauc": 0.9819631346827999,
            "ap": 0.9718142297566985,
            "f1": 0.9456066945606695,
            "entropy_rauc": 0.3459044818877455,
            "entropy_ap": 0.4039502442640505,
            "entropy_f1": 0.3807531380753138,
            "avg_normal_entropy": 2.4405312538146973,
            "avg_abnormal_entropy": 2.3596205711364746,
            "avg_normal_recon": 0.7298198938369751,
            "avg_abnormal_recon": 18.92990493774414
        },
        {
            "run": 4,
            "train_time": 12.98207950592041,
            "test_time": 0.0698249340057373,
            "epochs": 79,
            "rauc": 0.9822646914697124,
            "ap": 0.9810747785827227,
            "f1": 0.9372384937238494,
            "entropy_rauc": 0.26408835613856535,
            "entropy_ap": 0.3785579881535545,
            "entropy_f1": 0.3263598326359833,
            "avg_normal_entropy": 2.3508689403533936,
            "avg_abnormal_entropy": 2.184229612350464,
            "avg_normal_recon": 0.5527257919311523,
            "avg_abnormal_recon": 14.21540641784668
        },
        {
            "run": 5,
            "train_time": 21.970832586288452,
            "test_time": 0.06448674201965332,
            "epochs": 134,
            "rauc": 0.9795129857891365,
            "ap": 0.9771399295659013,
            "f1": 0.9288702928870293,
            "entropy_rauc": 0.4308681066003242,
            "entropy_ap": 0.4366342689489315,
            "entropy_f1": 0.4811715481171548,
            "avg_normal_entropy": 2.429471969604492,
            "avg_abnormal_entropy": 2.3904030323028564,
            "avg_normal_recon": 0.3750416934490204,
            "avg_abnormal_recon": 11.510647773742676
        },
        {
            "run": 6,
            "train_time": 9.539592504501343,
            "test_time": 0.06493425369262695,
            "epochs": 57,
            "rauc": 0.9862414715971202,
            "ap": 0.9848125470303692,
            "f1": 0.9539748953974896,
            "entropy_rauc": 0.2812393983942101,
            "entropy_ap": 0.38664382947976594,
            "entropy_f1": 0.3682008368200837,
            "avg_normal_entropy": 2.4406654834747314,
            "avg_abnormal_entropy": 2.236072301864624,
            "avg_normal_recon": 0.38641494512557983,
            "avg_abnormal_recon": 13.620828628540039
        },
        {
            "run": 7,
            "train_time": 15.96351432800293,
            "test_time": 0.06476640701293945,
            "epochs": 97,
            "rauc": 0.9789664141128577,
            "ap": 0.9725791162828705,
            "f1": 0.9456066945606695,
            "entropy_rauc": 0.3361133099626824,
            "entropy_ap": 0.40121133047262697,
            "entropy_f1": 0.3807531380753138,
            "avg_normal_entropy": 2.4025185108184814,
            "avg_abnormal_entropy": 2.2774734497070312,
            "avg_normal_recon": 0.528287410736084,
            "avg_abnormal_recon": 11.807251930236816
        },
        {
            "run": 8,
            "train_time": 15.95999026298523,
            "test_time": 0.048383235931396484,
            "epochs": 97,
            "rauc": 0.9796826114817747,
            "ap": 0.9776761555697189,
            "f1": 0.9330543933054394,
            "entropy_rauc": 0.2316521542462965,
            "entropy_ap": 0.3712172402864392,
            "entropy_f1": 0.3514644351464435,
            "avg_normal_entropy": 2.464315414428711,
            "avg_abnormal_entropy": 2.207711935043335,
            "avg_normal_recon": 0.3069798946380615,
            "avg_abnormal_recon": 7.3875250816345215
        },
        {
            "run": 9,
            "train_time": 13.722534894943237,
            "test_time": 0.06400728225708008,
            "epochs": 83,
            "rauc": 0.9855818161257492,
            "ap": 0.9854747145669305,
            "f1": 0.9330543933054394,
            "entropy_rauc": 0.1866448037996155,
            "entropy_ap": 0.3576356757672126,
            "entropy_f1": 0.30962343096234307,
            "avg_normal_entropy": 2.420614719390869,
            "avg_abnormal_entropy": 2.1277756690979004,
            "avg_normal_recon": 0.3413648307323456,
            "avg_abnormal_recon": 12.698481559753418
        }
    ]
}