{
    "model_config": {
        "num_features": 62,
        "model_type": "KNN"
    },
    "train_config": {
        "data_dir": "Data/",
        "random_seed": 42,
        "num_workers": 0,
        "batch_size": 512,
        "preprocess": "standard",
        "learning_rate": null,
        "model_type": "KNN",
        "dataset_name": "dependency_anomalies_5_campaign_42",
        "train_ratio": 1.0,
        "base_path": "results/KNN/dependency_anomalies_5_campaign_42/1.0",
        "run": 9
    },
    "mean_metrics": {
        "AUC-ROC": 0.9213883513603275,
        "AUC-PR": 0.6543608827395514,
        "f1": 0.6683836206896552
    },
    "total_time": 146.40732312202454,
    "all_seeds": [
        {
            "run": 0,
            "AUC-ROC": 0.9212548896491342,
            "AUC-PR": 0.6564370131920811,
            "f1": 0.66875
        },
        {
            "run": 1,
            "AUC-ROC": 0.9209336776765934,
            "AUC-PR": 0.6470212797253725,
            "f1": 0.6709051724137931
        },
        {
            "run": 2,
            "AUC-ROC": 0.9214724471927327,
            "AUC-PR": 0.6546831965943013,
            "f1": 0.6704741379310345
        },
        {
            "run": 3,
            "AUC-ROC": 0.9230759478324208,
            "AUC-PR": 0.6669823736532859,
            "f1": 0.6721982758620689
        },
        {
            "run": 4,
            "AUC-ROC": 0.9207968005230723,
            "AUC-PR": 0.651216908716365,
            "f1": 0.6661637931034483
        },
        {
            "run": 5,
            "AUC-ROC": 0.9208465579511874,
            "AUC-PR": 0.65524714768635,
            "f1": 0.665301724137931
        },
        {
            "run": 6,
            "AUC-ROC": 0.9215262616379781,
            "AUC-PR": 0.6590302981531769,
            "f1": 0.6665948275862069
        },
        {
            "run": 7,
            "AUC-ROC": 0.9208916450921415,
            "AUC-PR": 0.651452502004051,
            "f1": 0.665301724137931
        },
        {
            "run": 8,
            "AUC-ROC": 0.9218363168134113,
            "AUC-PR": 0.6528176215096959,
            "f1": 0.6685344827586207
        },
        {
            "run": 9,
            "AUC-ROC": 0.9212489692346013,
            "AUC-PR": 0.6487204861608344,
            "f1": 0.6696120689655173
        }
    ]
}