{
    "model_config": {
        "mask_num": 15,
        "lambda": 100,
        "en_nlayers": 3,
        "de_nlayers": 3,
        "hidden_dim": 256,
        "z_dim": 128,
        "mask_nlayers": 3,
        "num_features": 9
    },
    "train_config": {
        "data_dir": "Data/",
        "epochs": 200,
        "learning_rate": 0.05,
        "sche_gamma": 0.98,
        "batch_size": 512,
        "random_seed": 42,
        "num_workers": 0,
        "preprocess": "standard",
        "model_type": "MCM",
        "dataset_name": "glass",
        "train_ratio": 0.3,
        "base_path": "results/MCM/glass/0.3",
        "not_use_power_of_two": false,
        "num_memories_not_use_power_of_two": false,
        "num_memories_twice": false,
        "contamination_ratio": null,
        "latent_ratio": null,
        "memory_ratio": null,
        "run": 9
    },
    "mean_metrics": {
        "AUC-ROC": 0.7660194174757281,
        "AUC-PR": 0.22400385211998558,
        "f1": 0.15555555555555553
    },
    "total_time": 86.02306270599365,
    "all_seeds": [
        {
            "run": 0,
            "AUC-ROC": 0.7874865156418555,
            "AUC-PR": 0.2789071200705934,
            "f1": 0.1111111111111111
        },
        {
            "run": 1,
            "AUC-ROC": 0.7702265372168284,
            "AUC-PR": 0.29052278469921544,
            "f1": 0.3333333333333333
        },
        {
            "run": 2,
            "AUC-ROC": 0.8090614886731391,
            "AUC-PR": 0.3043040374776509,
            "f1": 0.2222222222222222
        },
        {
            "run": 3,
            "AUC-ROC": 0.819848975188781,
            "AUC-PR": 0.21219029803561068,
            "f1": 0.1111111111111111
        },
        {
            "run": 4,
            "AUC-ROC": 0.7259978425026969,
            "AUC-PR": 0.16375313328241628,
            "f1": 0.1111111111111111
        },
        {
            "run": 5,
            "AUC-ROC": 0.7022653721682848,
            "AUC-PR": 0.1622570714394262,
            "f1": 0.1111111111111111
        },
        {
            "run": 6,
            "AUC-ROC": 0.7831715210355987,
            "AUC-PR": 0.17119241272467078,
            "f1": 0.1111111111111111
        },
        {
            "run": 7,
            "AUC-ROC": 0.6612729234088457,
            "AUC-PR": 0.14692384594345378,
            "f1": 0.1111111111111111
        },
        {
            "run": 8,
            "AUC-ROC": 0.7842502696871628,
            "AUC-PR": 0.20449879198169213,
            "f1": 0.1111111111111111
        },
        {
            "run": 9,
            "AUC-ROC": 0.8166127292340883,
            "AUC-PR": 0.3054890255451265,
            "f1": 0.2222222222222222
        }
    ]
}