{
    "model_config": {
        "num_features": 9,
        "model_type": "LOF"
    },
    "train_config": {
        "data_dir": "Data/",
        "random_seed": 42,
        "num_workers": 0,
        "batch_size": 512,
        "preprocess": "standard",
        "learning_rate": null,
        "model_type": "LOF",
        "dataset_name": "cluster_anomalies_4_breastw_42",
        "train_ratio": 1.0,
        "base_path": "results/LOF/cluster_anomalies_4_breastw_42/1.0",
        "not_use_power_of_two": false,
        "num_memories_not_use_power_of_two": false,
        "num_memories_twice": false,
        "contamination_ratio": null,
        "latent_ratio": null,
        "memory_ratio": null,
        "run": 9
    },
    "mean_metrics": {
        "AUC-ROC": 0.9837008556673827,
        "AUC-PR": 0.9617725785013057,
        "f1": 0.9732217573221759
    },
    "total_time": 0.6734113693237305,
    "all_seeds": [
        {
            "run": 0,
            "AUC-ROC": 0.9873157676504958,
            "AUC-PR": 0.9632090189151334,
            "f1": 0.9832635983263598
        },
        {
            "run": 1,
            "AUC-ROC": 0.9881073542161408,
            "AUC-PR": 0.9708718741775515,
            "f1": 0.9790794979079498
        },
        {
            "run": 2,
            "AUC-ROC": 0.9848467714576502,
            "AUC-PR": 0.9648071954442758,
            "f1": 0.9707112970711297
        },
        {
            "run": 3,
            "AUC-ROC": 0.98475253496174,
            "AUC-PR": 0.9536750703042003,
            "f1": 0.9748953974895398
        },
        {
            "run": 4,
            "AUC-ROC": 0.9840551848920048,
            "AUC-PR": 0.9606814366688875,
            "f1": 0.9790794979079498
        },
        {
            "run": 5,
            "AUC-ROC": 0.9808511440310603,
            "AUC-PR": 0.9545335877675349,
            "f1": 0.9665271966527197
        },
        {
            "run": 6,
            "AUC-ROC": 0.9874665460439519,
            "AUC-PR": 0.9730593577063839,
            "f1": 0.9790794979079498
        },
        {
            "run": 7,
            "AUC-ROC": 0.9795318330883185,
            "AUC-PR": 0.9491167338129878,
            "f1": 0.9665271966527197
        },
        {
            "run": 8,
            "AUC-ROC": 0.9786648573259451,
            "AUC-PR": 0.9664004688147083,
            "f1": 0.9623430962343096
        },
        {
            "run": 9,
            "AUC-ROC": 0.981416563006521,
            "AUC-PR": 0.961371041401395,
            "f1": 0.9707112970711297
        }
    ]
}